README
setup.py
RODeco/RODeco.py
RODeco/__init__.py
RODeco.egg-info/PKG-INFO
RODeco.egg-info/SOURCES.txt
RODeco.egg-info/dependency_links.txt
RODeco.egg-info/top_level.txt