Metadata-Version: 1.1
Name: RODeco
Version: 1.0
Summary: RODeco a read only function decorator
Home-page: https://github.com/Arzaroth/RODeco
Author: Lucas Philippe, Marc-Etienne Barrut
Author-email: lu.k.philippe@gmail.com, me.barrut@gmail.com
License: GPLv3
Download-URL: https://github.com/Arzaroth/RODeco/tarball/1.0
Platform: UNKNOWN
